Workbook
Name FC_AMT: Inputs!$C$4
Name R_USD: Inputs!$C$7
Name PREM_PUT: Inputs!$C$11
Name K_CALL: Inputs!$C$10
Name S0_in: Inputs!$C$5
Name PREM_CALL: Inputs!$C$12
Name R_FC: Inputs!$C$8
Name K_PUT: Inputs!$C$9
Name T_DAYS: Inputs!$C$13
Name F0_in: Inputs!$C$6

Sheet Cover
A1: FX Hedging Financial Model
A3: Scenario: | B3: EUR 4.5M Receivable (1 Year)
A4: Author: | B4: Hai Duong
A5: Date: | B5: 46310
A6: Capability: | B6: fx-hedging
A7: Status: | B7: Stage 3 - Built & Audited
A8: Data Provenance: | B8: Indicative market placeholders (To be populated with live data in Stage 4)

Sheet Legend_Key
A1: Model Color Legend & Coding Standards
A3: Color Coding | B3: Description
A4: Yellow Fill | B4: Hardcoded Inputs (Editable)
A5: Blue Fill | B5: Model Assumptions & Parameters
A6: Green Fill | B6: Formula-Driven Calculations
A7: Gray Fill | B7: Key Summary Outputs

Sheet Inputs
A1: Model Inputs & Named Range Contract
A3: Named Range | B3: Description | C3: Placeholder Value | D3: Unit | E3: Stage 4 Data Source
A4: FC_AMT | B4: Foreign-currency receivable | C4: 4500000 | D4: EUR | E4: Invoice / Contract
A5: S0_in | B5: Spot exchange rate at inception | C5: 1.085 | D5: USD per EUR | E5: Live Spot FX Rate
A6: F0_in | B6: 1-Year Forward exchange rate | C6: 1.100745 | D6: USD per EUR | E6: Bank Forward Rate
A7: R_USD | B7: USD interest rate | C7: 0.0475 | D7: Annual % | E7: Fed H.15 Yield
A8: R_FC | B8: EUR interest rate | C8: 0.0325 | D8: Annual % | E8: ECB €STR Rate
A9: K_PUT | B9: Put option strike price | C9: 1.085 | D9: USD per EUR | E9: Option Desk Quote
A10: K_CALL | B10: Call option strike price | C10: 1.085 | D10: USD per EUR | E10: Option Desk Quote
A11: PREM_PUT | B11: Put option premium per unit | C11: 0.025 | D11: USD per EUR | E11: Option Desk Quote
A12: PREM_CALL | B12: Call option premium per unit | C12: 0.025 | D12: USD per EUR | E12: Option Desk Quote
A13: T_DAYS | B13: Days to settlement | C13: 360 | D13: Days | E13: Contract Term

Sheet Hedge_Calculations
A1: Hedge Strategy Calculations
A3: Strategy / Metric | B3: Formula Result (USD)
A4: Unhedged Baseline Proceeds | B4: =FC_AMT*S0_in -> 4882500
A5: Forward Hedge Proceeds | B5: =FC_AMT*F0_in -> 4953352.5
A6: MM Step 1: Foreign Currency Borrowed | B6: =FC_AMT/(1+R_FC*T_DAYS/360) -> 4358353.5
A7: MM Step 2: USD Converted at Spot | B7: =B6*S0_in -> 4728813.6
A8: MM Step 3: Final USD Proceeds | B8: =B7*(1+R_USD*T_DAYS/360) -> 4953432.2
A9: Option Gross Proceeds | B9: =FC_AMT*MAX(S0_in, K_PUT) -> 4882500
A10: Option Total Premium Paid | B10: =FC_AMT*PREM_PUT -> 112500
A11: Option Net Proceeds | B11: =B9-B10 -> 4770000

Sheet Sensitivity_Analysis
A1: Sensitivity Analysis (-5% to +5% Spot Move)
A3: Spot Scenario (% S0) | B3: Settlement Spot (S_T) | C3: Unhedged Proceeds | D3: Forward Proceeds | E3: MM Hedge Proceeds | F3: Option Net Proceeds
A4: -0.05 | B4: =S0_in*(1+A4) -> 1.03075 | C4: =FC_AMT*B4 -> 4638375 | D4: =FC_AMT*F0_in -> 4953352.5 | E4: =Hedge_Calculations!B8 -> 4953432.2 | F4: =FC_AMT*MAX(B4, K_PUT)-(FC_AMT*PREM_PUT) -> 4770000
A5: -0.04 | B5: =S0_in*(1+A5) -> 1.0416 | C5: =FC_AMT*B5 -> 4687200 | D5: =FC_AMT*F0_in -> 4953352.5 | E5: =Hedge_Calculations!B8 -> 4953432.2 | F5: =FC_AMT*MAX(B5, K_PUT)-(FC_AMT*PREM_PUT) -> 4770000
A6: -0.03 | B6: =S0_in*(1+A6) -> 1.05245 | C6: =FC_AMT*B6 -> 4736025 | D6: =FC_AMT*F0_in -> 4953352.5 | E6: =Hedge_Calculations!B8 -> 4953432.2 | F6: =FC_AMT*MAX(B6, K_PUT)-(FC_AMT*PREM_PUT) -> 4770000
A7: -0.02 | B7: =S0_in*(1+A7) -> 1.0633 | C7: =FC_AMT*B7 -> 4784850 | D7: =FC_AMT*F0_in -> 4953352.5 | E7: =Hedge_Calculations!B8 -> 4953432.2 | F7: =FC_AMT*MAX(B7, K_PUT)-(FC_AMT*PREM_PUT) -> 4770000
A8: -0.01 | B8: =S0_in*(1+A8) -> 1.07415 | C8: =FC_AMT*B8 -> 4833675 | D8: =FC_AMT*F0_in -> 4953352.5 | E8: =Hedge_Calculations!B8 -> 4953432.2 | F8: =FC_AMT*MAX(B8, K_PUT)-(FC_AMT*PREM_PUT) -> 4770000
A9: 0 | B9: =S0_in*(1+A9) -> 1.085 | C9: =FC_AMT*B9 -> 4882500 | D9: =FC_AMT*F0_in -> 4953352.5 | E9: =Hedge_Calculations!B8 -> 4953432.2 | F9: =FC_AMT*MAX(B9, K_PUT)-(FC_AMT*PREM_PUT) -> 4770000
A10: 0.01 | B10: =S0_in*(1+A10) -> 1.09585 | C10: =FC_AMT*B10 -> 4931325 | D10: =FC_AMT*F0_in -> 4953352.5 | E10: =Hedge_Calculations!B8 -> 4953432.2 | F10: =FC_AMT*MAX(B10, K_PUT)-(FC_AMT*PREM_PUT) -> 4818825
A11: 0.02 | B11: =S0_in*(1+A11) -> 1.1067 | C11: =FC_AMT*B11 -> 4980150 | D11: =FC_AMT*F0_in -> 4953352.5 | E11: =Hedge_Calculations!B8 -> 4953432.2 | F11: =FC_AMT*MAX(B11, K_PUT)-(FC_AMT*PREM_PUT) -> 4867650
A12: 0.03 | B12: =S0_in*(1+A12) -> 1.11755 | C12: =FC_AMT*B12 -> 5028975 | D12: =FC_AMT*F0_in -> 4953352.5 | E12: =Hedge_Calculations!B8 -> 4953432.2 | F12: =FC_AMT*MAX(B12, K_PUT)-(FC_AMT*PREM_PUT) -> 4916475
A13: 0.04 | B13: =S0_in*(1+A13) -> 1.1284 | C13: =FC_AMT*B13 -> 5077800 | D13: =FC_AMT*F0_in -> 4953352.5 | E13: =Hedge_Calculations!B8 -> 4953432.2 | F13: =FC_AMT*MAX(B13, K_PUT)-(FC_AMT*PREM_PUT) -> 4965300
A14: 0.05 | B14: =S0_in*(1+A14) -> 1.13925 | C14: =FC_AMT*B14 -> 5126625 | D14: =FC_AMT*F0_in -> 4953352.5 | E14: =Hedge_Calculations!B8 -> 4953432.2 | F14: =FC_AMT*MAX(B14, K_PUT)-(FC_AMT*PREM_PUT) -> 5014125

Sheet Validation_Checks
A1: Workbook Audit & Validation Checks
A3: Check Item | B3: Value / Formula | C3: Status
A4: Covered Interest Parity Implied Forward | B4: =S0_in*(1+R_USD*T_DAYS/360)/(1+R_FC*T_DAYS/360) -> 1.1007627 | C4: Calculated Implied Forward
A5: Forward vs MM Variance | B5: =ABS(Hedge_Calculations!B8 - Hedge_Calculations!B5) -> 79.70339 | C5: USD Variance
A6: Parity Audit Status | B6: =IF(B5<0.01, "PASS", "FAIL") -> FAIL | C6: Audit Pass/Fail Status
